LICENSE
README.md
setup.py
aiozyre.egg-info/PKG-INFO
aiozyre.egg-info/SOURCES.txt
aiozyre.egg-info/dependency_links.txt
aiozyre.egg-info/not-zip-safe
aiozyre.egg-info/requires.txt
aiozyre.egg-info/top_level.txt
src/aiozyre/__init__.py
src/aiozyre/exceptions.py
src/aiozyre/futures.py
src/aiozyre/messages.py
src/aiozyre/node.py
src/aiozyre/nodeactor.c
src/aiozyre/nodeactor.pxd
src/aiozyre/nodeactor.pyx
src/aiozyre/nodeconfig.py
src/aiozyre/signals.c
src/aiozyre/signals.pxd
src/aiozyre/signals.pyx
src/aiozyre/util.c
src/aiozyre/util.pxd
src/aiozyre/util.pyx
src/aiozyre/zyre.pxd