Metadata-Version: 2.1
Name: aiozyre
Version: 1.1.5
Summary: asyncio-friendly Python bindings for Zyre
Home-page: UNKNOWN
Author: Elijah Shaw-Rutschman
Author-email: elijahr+aiozyre@gmail.com
License: UNKNOWN
Platform: UNKNOWN
Classifier: Environment :: Console
Classifier: Intended Audience :: Developers
Classifier: License :: OSI Approved :: BSD License
Classifier: Operating System :: MacOS :: MacOS X
Classifier: Programming Language :: Python :: 3
Classifier: Programming Language :: Python :: 3
Classifier: Topic :: System :: Networking
Classifier: Framework :: AsyncIO
Provides-Extra: dev
